pyarv/__init__.py
pyarv/_approximation_utils/__init__.py
pyarv/_approximation_utils/approximating_polynomials.py
pyarv/approximations/__init__.py
pyarv/approximations/polynomial_approximations.py
pyarv/gaussian/__init__.py
pyarv/gaussian/approximation.py
pyarv/gaussian/gaussian_bindings.cpython-312-darwin.so
pyarv/gaussian/polynomial.py
pyarv/gaussian/demos/__init__.py
pyarv/gaussian/demos/accuracy.py
pyarv/gaussian/demos/speed.py
pyarv/gaussian/tests/__init__.py
pyarv/gaussian/tests/test_gaussian_bindings.py
pyarv/non_central_chi_squared/__init__.py
pyarv/non_central_chi_squared/_approximate_non_central_chi_squared.py
pyarv/non_central_chi_squared/_approximate_non_central_chi_squared_demonstrations.py
pyarv/non_central_chi_squared/_table_coefficients.py
pyarv/non_central_chi_squared/approximate_non_central_chi_squared.py
pyarv/non_central_chi_squared/approximate_non_central_chi_squared_demonstrations.py
pyarv/non_central_chi_squared/approximation.py
pyarv/non_central_chi_squared/non_central_chi_squared_bindings.cpython-312-darwin.so
pyarv/non_central_chi_squared/polynomial.py
pyarv/non_central_chi_squared/table_coefficients.py
pyarv/non_central_chi_squared/demos/__init__.py
pyarv/non_central_chi_squared/demos/accuracy.py
pyarv/non_central_chi_squared/demos/speed.py
pyarv/non_central_chi_squared/tests/__init__.py
pyarv/non_central_chi_squared/tests/test_non_central_chi_squared_bindings.py
pyarv/type_hints/__init__.py
pyarv/type_hints/arrays.py
pyarv/version/__init__.py
pyarv/version/version_bindings.cpython-312-darwin.so
pyarv/version/tests/__init__.py
pyarv/version/tests/test_version_bindings.py
PyARV-0.2.5.dist-info/LICENSE.md
PyARV-0.2.5.dist-info/METADATA
PyARV-0.2.5.dist-info/WHEEL
PyARV-0.2.5.dist-info/top_level.txt
PyARV-0.2.5.dist-info/RECORD
